openmodels/__init__.py
openmodels/converters/__init__.py
openmodels/converters/json_converter.py
openmodels/converters/pickle_converter.py
openmodels/core.py
openmodels/exceptions.py
openmodels/format_registry.py
openmodels/protocols.py
openmodels/serializers/__init__.py
openmodels/serializers/base.py
openmodels/serializers/sklearn/__init__.py
openmodels/serializers/sklearn/_custom_estimator.py
openmodels/serializers/sklearn/sklearn_serializer.py
openmodels/test_helpers.py
openmodels-0.1.0a20.dist-info/METADATA
openmodels-0.1.0a20.dist-info/WHEEL
openmodels-0.1.0a20.dist-info/licenses/LICENSE
openmodels-0.1.0a20.dist-info/RECORD
