Metadata-Version: 2.4
Name: openmodels
Version: 0.1.0a20
Summary: Export scikit-learn model files to JSON for sharing or deploying predictive models with peace of mind.
License: MIT
License-File: LICENSE
Author: Alejandro Gutierrez
Author-email: agutierrez@sftec.es>, Pau Cabaneros <pau.cabaneros@gmail.com>, Raúl Marín <hi@raulmarin.dev>, Ruben Parrilla <rparrilla@sftec.es
Requires-Python: >=3.10,<4.0
Classifier: License :: OSI Approved :: MIT License
Classifier: Programming Language :: Python :: 3
Classifier: Programming Language :: Python :: 3.10
Classifier: Programming Language :: Python :: 3.11
Classifier: Programming Language :: Python :: 3.12
Classifier: Programming Language :: Python :: 3.13
Classifier: Programming Language :: Python :: 3.14
Requires-Dist: scikit-learn (>=1.6.0,<2.0.0)
